text_to_markdown_jxppx/__init__.py
text_to_markdown_jxppx/tt_md.py
text_to_markdown_jxppx-1.0.0.dist-info/licenses/LICENSE
text_to_markdown_jxppx-1.0.0.dist-info/METADATA
text_to_markdown_jxppx-1.0.0.dist-info/WHEEL
text_to_markdown_jxppx-1.0.0.dist-info/entry_points.txt
text_to_markdown_jxppx-1.0.0.dist-info/top_level.txt
text_to_markdown_jxppx-1.0.0.dist-info/RECORD
