Metadata-Version: 2.4
Name: text_to_markdown_jxppx
Version: 1.0.0
Summary: 用于将文本文件转化为markdown格式
Author-email: wangkun <17621177409@163.com>
Project-URL: Homepage, https://github.com/yourusername/text_to_markdown_jxppx
Project-URL: Repository, https://github.com/yourusername/text_to_markdown_jxppx
Project-URL: Issues, https://github.com/yourusername/text_to_markdown_jxppx/issues
Classifier: Programming Language :: Python :: 3
Classifier: License :: OSI Approved :: MIT License
Classifier: Operating System :: OS Independent
Requires-Python: >=3.8
License-File: LICENSE
Provides-Extra: dev
Requires-Dist: pytest>=7.0.0; extra == "dev"
Requires-Dist: pytest-cov>=4.0.0; extra == "dev"
Requires-Dist: black>=22.0.0; extra == "dev"
Requires-Dist: flake8>=5.0.0; extra == "dev"
Provides-Extra: enhanced
Requires-Dist: chardet>=5.0.0; extra == "enhanced"
Requires-Dist: python-magic>=0.4.27; extra == "enhanced"
Dynamic: license-file
